applab/core/__init__.py
applab/core/_cli/__init__.py
applab/core/_cli/main.py
applab/core/_cli/provider.py
applab/core/core.py
applab/core/main.py
applab/core/provider/__init__.py
applab/core/provider/base.py
applab/core/provider/provider.py
applab/core/provider/tencentcloud/__init__.py
applab/core/py.typed
applab_core-0.0.2.dev20251230153900.dist-info/WHEEL
applab_core-0.0.2.dev20251230153900.dist-info/entry_points.txt
applab_core-0.0.2.dev20251230153900.dist-info/METADATA
applab_core-0.0.2.dev20251230153900.dist-info/RECORD
