Metadata-Version: 2.3
Name: applab-core
Version: 0.0.2.dev20251230153900
Summary: Add your description here
Author: Chen Peng
License: MIT
Requires-Dist: cyclopts>=4.4.0
Requires-Dist: pydantic>=2.12.5
Requires-Dist: requests>=2.32.5
Requires-Dist: rich>=14.2.0
Requires-Dist: tencentcloud-sdk-python-common>=3.1.12
Requires-Python: >=3.12
Project-URL: homepage, https://github.com/chen56/applab
